sttool/__init__.py
sttool/app.py
sttool/cli.py
sttool/py.typed
sttool/templates/config/application.properties
sttool/templates/config/crypto_config.properties
sttool/templates/config/limas.properties
sttool/templates/simulation/C220A_simulation.txt
sttool/templates/simulation/C320B_simulation.txt
sttool/templates/simulation/C320C_simulation.txt
sttool/templates/simulation/M219B_simulation.txt
sttool/templates/simulation/M219P14_simulation.txt
sttool/templates/simulation/M219P_simulation.txt
sttool/templates/simulation/S219A_simulation.txt
sttool/templates/simulation/YYDGW_simulation.txt
sttool/templates/simulation/YYDSH_simulation.txt
sttool/templates/simulation/YYNVA_simulation.txt
sttool-0.1.1.dist-info/entry_points.txt
sttool-0.1.1.dist-info/LICENSE
sttool-0.1.1.dist-info/METADATA
sttool-0.1.1.dist-info/WHEEL
sttool-0.1.1.dist-info/RECORD
