Metadata-Version: 2.1
Name: sttool
Version: 0.1.1
Summary: Simple command line tools for testing tasks
Home-page: https://github.com/MrSuperbear/sttool
License: Proprietary
Author: Darrin Fraser
Author-email: darrin.fraser@agcocorp.com
Requires-Python: >=3.8.0,<4.0.0
Classifier: Development Status :: 1 - Planning
Classifier: Environment :: Console
Classifier: License :: Other/Proprietary License
Classifier: Programming Language :: Python :: 3
Classifier: Programming Language :: Python :: 3.8
Classifier: Programming Language :: Python :: 3.9
Classifier: Programming Language :: Python :: 3.10
Classifier: Programming Language :: Python :: 3.11
Requires-Dist: Jinja2 (>=3.1.2,<4.0.0)
Requires-Dist: PyYAML (>=5.4.1,<6.0.0)
Requires-Dist: click (>=8.0.1,<9.0.0)
Requires-Dist: parse (>=1.19.0,<2.0.0)
Requires-Dist: pypsexec (>=0.3.0,<0.4.0)
Requires-Dist: requests (>=2.28.0,<3.0.0)
Requires-Dist: rich (>=12.4.4,<13.0.0)
Requires-Dist: system-info (>=2.0.0,<3.0.0)
Project-URL: Bug Tracker, https://github.com/MrSuperbear/sttool/issues
Project-URL: Documentation, https://github.com/MrSuperbear/sttool/blob/master/README.md
Project-URL: Repository, https://github.com/MrSuperbear/sttool
